{"chunk_definitions":[{"row":16,"row_count":1,"visible":true,"expansion_state":0,"options":{"engine":"r","label":"setup","include":false},"document_id":"8D5638F1","chunk_id":"csetup_chunk","chunk_label":"setup"},{"row":34,"row_count":1,"visible":true,"expansion_state":0,"options":{"engine":"r","label":"loadpacks","message":false,"results":"hide"},"document_id":"8D5638F1","chunk_id":"clx9s8eupmlmg","chunk_label":"loadpacks"},{"row":59,"row_count":1,"visible":true,"expansion_state":0,"options":{"engine":"r","label":"answer1","echo":false,"eval":false},"document_id":"8D5638F1","chunk_id":"cqs4kusdzkmfc","chunk_label":"unnamed-chunk-1"},{"row":69,"row_count":1,"visible":true,"expansion_state":0,"options":{"engine":"r","label":"answer2","echo":true,"eval":false},"document_id":"8D5638F1","chunk_id":"cpsal366atynj","chunk_label":"answer2"},{"row":99,"row_count":1,"visible":true,"expansion_state":0,"options":{"engine":"r","label":"loaddata","eval":false,"echo":true},"document_id":"8D5638F1","chunk_id":"c308931b2hz7i","chunk_label":"unnamed-chunk-2"},{"row":120,"row_count":1,"visible":true,"expansion_state":0,"options":{"engine":"r","label":"rmMiss"},"document_id":"8D5638F1","chunk_id":"cb62uj0wzfx69","chunk_label":"unnamed-chunk-4"},{"row":135,"row_count":1,"visible":true,"expansion_state":0,"options":{"engine":"r","label":"summaryTab"},"document_id":"8D5638F1","chunk_id":"cyc49mhe3gsgz","chunk_label":"summaryTab"},{"row":145,"row_count":1,"visible":true,"expansion_state":0,"options":{"engine":"r","label":"example-flextable-flextable-15"},"document_id":"8D5638F1","chunk_id":"cpsgbz3r57ww1","chunk_label":"unnamed-chunk-5"},{"row":165,"row_count":1,"visible":true,"expansion_state":0,"options":{"engine":"r","label":"prettyfig","fig.align":"center","fig.cap":"add a legend here"},"document_id":"8D5638F1","chunk_id":"cqodmuvq02ti4","chunk_label":"unnamed-chunk-6"},{"row":171,"row_count":1,"visible":true,"expansion_state":0,"options":{"engine":"r","label":"example-flextable-flextable-16"},"document_id":"8D5638F1","chunk_id":"cep48cp2t8q2r","chunk_label":"unnamed-chunk-7"},{"row":180,"row_count":1,"visible":true,"expansion_state":0,"options":{"engine":"r","label":"savefig"},"document_id":"8D5638F1","chunk_id":"cbcoe94z8tx4r","chunk_label":"unnamed-chunk-8"}],"doc_write_time":1662461005,"working_dir":null,"default_chunk_options":{"echo":true}}